pydboat-1.0.9.data/data/cl100k_base.tiktoken
src/__init__.py
src/resource/__init__.py
pydboat-1.0.9.dist-info/LICENSE
pydboat-1.0.9.dist-info/METADATA
pydboat-1.0.9.dist-info/WHEEL
pydboat-1.0.9.dist-info/top_level.txt
pydboat-1.0.9.dist-info/RECORD
